jackson_easy_api/__init__.py
jackson_easy_api/cli.py
jackson_easy_api/manage.py
jackson_easy_api-0.3.308.dist-info/LICENSE
jackson_easy_api-0.3.308.dist-info/METADATA
jackson_easy_api-0.3.308.dist-info/WHEEL
jackson_easy_api-0.3.308.dist-info/entry_points.txt
jackson_easy_api-0.3.308.dist-info/RECORD
