Metadata-Version: 2.1
Name: jackson_easy_api
Version: 0.3.308
Summary: A FastAPI project generator
License: MIT
Author: jacksonsr451
Author-email: jacksonsr451@gmail.com
Requires-Python: >=3.11,<4.0
Classifier: License :: OSI Approved :: MIT License
Classifier: Programming Language :: Python :: 3
Classifier: Programming Language :: Python :: 3.11
Classifier: Programming Language :: Python :: 3.12
Classifier: Programming Language :: Python :: 3.13
Requires-Dist: alembic (>=1.14.0,<2.0.0)
Requires-Dist: blue (>=0.9.1,<0.10.0)
Requires-Dist: isort (>=5.13.2,<6.0.0)
Requires-Dist: psycopg2-binary (>=2.9.10,<3.0.0)
Requires-Dist: pytest (>=8.3.3,<9.0.0)
Requires-Dist: python-decouple (>=3.8,<4.0)
Requires-Dist: sqlalchemy (>=2.0.36,<3.0.0)
